pycfalias/__init__.py
pycfalias/config.py
pycfalias/formatting.py
pycfalias/pycfalias.py
pycfalias-0.0.8.dist-info/LICENSE
pycfalias-0.0.8.dist-info/METADATA
pycfalias-0.0.8.dist-info/WHEEL
pycfalias-0.0.8.dist-info/entry_points.txt
pycfalias-0.0.8.dist-info/top_level.txt
pycfalias-0.0.8.dist-info/RECORD
