Metadata-Version: 2.1
Name: pycfalias
Version: 0.0.8
Summary: Simple Cloudflare email alias management
Home-page: https://github.com/ellie-gar/pycfalias
Author: Eliel Garcia
Author-email: inbox@eliel-garcia.com
Classifier: Programming Language :: Python :: 3
Classifier: License :: OSI Approved :: MIT License
Classifier: Operating System :: OS Independent
Requires-Python: >=3.6
License-File: LICENSE
Requires-Dist: prettytable (~=3.6.0)
